analyse_wo/__init__.py
analyse_wo/main.py
analyse_wo-0.1.5.dist-info/entry_points.txt
analyse_wo-0.1.5.dist-info/WHEEL
analyse_wo-0.1.5.dist-info/METADATA
analyse_wo-0.1.5.dist-info/RECORD
