Metadata-Version: 2.1
Name: analyse-wo
Version: 0.1.5
Summary: Analyse WO's in M3
Author: Kim Timothy Engh
Author-email: kimothy@users.noreply.github.com
Requires-Python: >=3.9,<4.0
Classifier: Programming Language :: Python :: 3
Classifier: Programming Language :: Python :: 3.10
Classifier: Programming Language :: Python :: 3.9
Requires-Dist: getting-and-setting (>=0.3.17,<0.4.0)
Requires-Dist: pandas (>=1.4.2,<2.0.0)
